obs_waykey/__init__.py
obs_waykey/toggles_ignition.py
obs_waykey/toggles_logic.py
obs_waykey-0.2.0.dist-info/LICENSE
obs_waykey-0.2.0.dist-info/METADATA
obs_waykey-0.2.0.dist-info/WHEEL
obs_waykey-0.2.0.dist-info/entry_points.txt
obs_waykey-0.2.0.dist-info/RECORD
