Metadata-Version: 2.1
Name: obs-waykey
Version: 0.2.0
Summary: OBS global shortcuts workaround for wayland using websocket
Author: PolyCat
Author-email: polycat@tuta.io
Requires-Python: >=3.9,<4.0
Classifier: Programming Language :: Python :: 3
Classifier: Programming Language :: Python :: 3.9
Classifier: Programming Language :: Python :: 3.10
Classifier: Programming Language :: Python :: 3.11
Classifier: Programming Language :: Python :: 3.12
Requires-Dist: obsws-python (>=1.7.0,<2.0.0)
